table_metrics/__init__.py
table_metrics/grits.py
table_metrics/teds.py
table_metrics-0.1.1.dist-info/LICENSE
table_metrics-0.1.1.dist-info/METADATA
table_metrics-0.1.1.dist-info/WHEEL
table_metrics-0.1.1.dist-info/RECORD
