Metadata-Version: 2.3
Name: table-metrics
Version: 0.1.1
Summary: Python library implementing GriTS and TEDS
Author: gu1show
Author-email: denissolovyov57@gmail.com
Requires-Python: >=3.13
Classifier: Programming Language :: Python :: 3
Classifier: Programming Language :: Python :: 3.13
Requires-Dist: apted (>=1.0.3,<2.0.0)
Requires-Dist: lxml (>=6.0.2,<7.0.0)
Requires-Dist: numpy (>=2.4.0,<3.0.0)
Requires-Dist: rapidfuzz (>=3.14.1,<4.0.0)
